mongo/__init__.py
mongo/core/__init__.py
mongo/core/base_mongo_dao.py
mongo/core/base_mongo_model.py
mongo/core/mongo_collection.py
mongo/core/mongo_connection.py
mongo/core/objectid.py
mongo/daos/__init__.py
mongo/daos/assignment_dao.py
mongo/daos/company_dao.py
mongo/daos/concilia_erp_sat_config_dao.py
mongo/daos/conciliation_report_dao.py
mongo/daos/customer_dao.py
mongo/daos/data_erp_config_dao.py
mongo/daos/datasource_config_dao.py
mongo/daos/datasource_upload_dao.py
mongo/daos/excel_data_type_dao.py
mongo/daos/project_dao.py
mongo/daos/project_type_dao.py
mongo/daos/report_type_dao.py
mongo/models/__init__.py
mongo/models/assignment.py
mongo/models/company.py
mongo/models/concilia_erp_sat_config.py
mongo/models/conciliation_report.py
mongo/models/customer.py
mongo/models/data_erp_config.py
mongo/models/datasource_config.py
mongo/models/datasource_upload.py
mongo/models/excel_data_type.py
mongo/models/project.py
mongo/models/project_type.py
mongo/models/report_config.py
mongo/models/report_type.py
mongo/pydantic_types/__init__.py
mongo/pydantic_types/date.py
mongo/pydantic_types/rfc_str.py
mongo/pydantic_types/uuid_str.py
s3/__init__.py
s3/files/__init__.py
s3/files/aws_wrapper.py
s3/files/bucket_manager.py
s3/files/file_manager.py
tools/__init__.py
tools/async_checker.py
tools/env.py
tools/datasources/__init__.py
tools/datasources/abc_datasource.py
tools/datasources/csv_datasource.py
tools/datasources/excel_datasource.py
conciliation_model-0.13.8.dist-info/LICENSE.txt
conciliation_model-0.13.8.dist-info/METADATA
conciliation_model-0.13.8.dist-info/WHEEL
conciliation_model-0.13.8.dist-info/top_level.txt
conciliation_model-0.13.8.dist-info/RECORD
