Metadata-Version: 2.1
Name: conciliation_model
Version: 0.13.8
Summary: Prueba
Author: Conciliaciones - Kuantik
Requires-Python: >=3.8
License-File: LICENSE.txt
Requires-Dist: fastapi>=0.110.2
Requires-Dist: pydantic>=2.7.1
Requires-Dist: pymongo>=4.7.0
Requires-Dist: inflect>=7.2.1
Requires-Dist: boto3>=1.34.99
Requires-Dist: boto3-stubs[s3]>=1.34.99
Requires-Dist: loggerk>=0.0.5
Requires-Dist: pandas>=2.2.2
